{
  "columns": [
    {
      "title": "B-CON Consulting",
      "links": [
        {
          "label": "Servicii",
          "href": "/servicii"
        },
        {
          "label": "Despre noi",
          "href": "/despre"
        }
      ]
    },
    {
      "title": "Resurse",
      "links": [
        {
          "label": "Blog",
          "href": "/blog"
        },
        {
          "label": "Contact",
          "href": "/contact"
        }
      ]
    }
  ],
  "contact": {
    "phone": "+40 0758 231 668",
    "email": "office@b-con.ro",
    "location": "România"
  },
  "legal": {
    "copyright": "© {{year}} B-CON Consulting. Toate drepturile rezervate."
  }
}
